docker_compose_expand/__init__.py
docker_compose_expand/cli.py
docker_compose_expand/core.py
docker_compose_expand/utils/template.py
docker_compose_expand/utils/yaml.py
docker_compose_expand-0.1.0.dist-info/entry_points.txt
docker_compose_expand-0.1.0.dist-info/WHEEL
docker_compose_expand-0.1.0.dist-info/METADATA
docker_compose_expand-0.1.0.dist-info/RECORD
